nenums/MS.py
nenums/XST.py
nenums/__init__.py
nenums/utils/__init__.py
nenums/utils/astro.py
nenums/utils/locationsSB2.dat
nenums/utils/makeant.py
nenums/utils/ms.py
nenums/utils/progressbar.py
nenums-0.0.8.data/scripts/nenums
nenums-0.0.8.data/scripts/nenuplotuv
nenums-0.0.8.dist-info/METADATA
nenums-0.0.8.dist-info/WHEEL
nenums-0.0.8.dist-info/top_level.txt
nenums-0.0.8.dist-info/RECORD
