Metadata-Version: 2.1
Name: nenums
Version: 0.0.8
Summary: NenuFAR XST to MS converter
Home-page: https://github.com/AlanLoh/nenums.git
Author: Alan Loh
Author-email: alan.loh@obspm.fr
License: MIT
Platform: UNKNOWN
Requires-Dist: numpy
Requires-Dist: astropy
